setup.py
async_get_vedio/__init__.py
async_get_vedio/get_vedio.py
async_get_vedio.egg-info/PKG-INFO
async_get_vedio.egg-info/SOURCES.txt
async_get_vedio.egg-info/dependency_links.txt
async_get_vedio.egg-info/top_level.txt