Metadata-Version: 2.1
Name: async-get-vedio
Version: 3.2
Summary: Get vedio
Home-page: https://github.com/wutljs/async_get_vedio
Author: WUT_ljs
Author-email: 3480339804@qq.com
License: UNKNOWN
Platform: UNKNOWN
Classifier: Programming Language :: Python :: 3
Classifier: License :: OSI Approved :: MIT License
Classifier: Operating System :: OS Independent
